rename-dirs/__init__.py
rename-dirs/__main__.py
rename_dirs/__init__.py
rename_dirs/__main__.py
rename_dirs-1.2.0.dist-info/LICENSE
rename_dirs-1.2.0.dist-info/METADATA
rename_dirs-1.2.0.dist-info/WHEEL
rename_dirs-1.2.0.dist-info/entry_points.txt
rename_dirs-1.2.0.dist-info/top_level.txt
rename_dirs-1.2.0.dist-info/RECORD
